stik/multistealer.py
stik/modules/__init__.py
stik/modules/chromium.py
stik/modules/system.py
stik/utils/__init__.py
stik/utils/config.py
stik/utils/sender.py
stik-0.0.1.dist-info/METADATA
stik-0.0.1.dist-info/WHEEL
stik-0.0.1.dist-info/top_level.txt
stik-0.0.1.dist-info/RECORD
